<?xml version="1.0" encoding="utf-8" ?>
<dwsync>
<file name="Master2_back-over.gif" local="126811188000000000" remote="126811188000000000" testing="0" />
<file name="Master2_back.gif" local="126811188000000000" remote="126811188000000000" testing="0" />
<file name="Master2_blue-left.gif" local="126811188000000000" remote="126811188000000000" testing="0" />
<file name="Master2_blue-right.gif" local="126811188000000000" remote="126811188000000000" testing="0" />
<file name="Master2_caillou-over.gif" local="126811188000000000" remote="126811188000000000" testing="0" />
<file name="Master2_caillou.gif" local="126811188000000000" remote="126811188000000000" testing="0" />
<file name="Master2_green-bottom.gif" local="126811188000000000" remote="126811188000000000" testing="0" />
<file name="Master2_green.gif" local="126811188000000000" remote="126811188000000000" testing="0" />
<file name="Master2_pbs.gif" local="126811188000000000" remote="126811188000000000" testing="0" />
<file name="Master2_red-bottom.gif" local="126811188000000000" remote="126811188000000000" testing="0" />
<file name="Master2_red.gif" local="126811188000000000" remote="126811188000000000" testing="0" />
<file name="Master2_yellow-left.gif" local="126811188000000000" remote="126811188000000000" testing="0" />
<file name="Master2_yellow-right.gif" local="126811188000000000" remote="126811188000000000" testing="0" />
<file name="Master_coloring-over.gif" local="128122473568125000" remote="128122473560000000" testing="0" />
<file name="Master_coloring.gif" local="128122473615312500" remote="128122473610000000" testing="0" />
<file name="Master_games-over.gif" local="128122473942656250" remote="128122473940000000" testing="0" />
<file name="Master_games.gif" local="128122473991718750" remote="128122473990000000" testing="0" />
<file name="Master_greetings-over.gif" local="128122473695781250" remote="128122473690000000" testing="0" />
<file name="Master_greetings.gif" local="128122473887968750" remote="128122473880000000" testing="0" />
<file name="paint_flashtext.gif" local="126815508000000000" remote="126815508000000000" testing="0" />
<file name="spacer.gif" local="126811188000000000" remote="126811188000000000" testing="0" />
<file name="spell_bottomborder.gif" local="126811188000000000" remote="126811188000000000" testing="0" />
<file name="spell_caillou_bottom.jpg" local="126811188000000000" remote="126811188000000000" testing="0" />
<file name="spell_caillou_top.jpg" local="126811188000000000" remote="126811188000000000" testing="0" />
<file name="spell_flashget-over.gif" local="126811188000000000" remote="126811188000000000" testing="0" />
<file name="spell_flashget.gif" local="126811188000000000" remote="126811188000000000" testing="0" />
<file name="spell_leftborder.gif" local="126811188000000000" remote="126811188000000000" testing="0" />
<file name="spell_play-over.gif" local="126811188000000000" remote="126811188000000000" testing="0" />
<file name="spell_play.gif" local="126811188000000000" remote="126811188000000000" testing="0" />
<file name="spell_rightborder.gif" local="126811188000000000" remote="126811188000000000" testing="0" />
<file name="spell_text.gif" local="126811188000000000" remote="126811188000000000" testing="0" />
<file name="spell_title.gif" local="126811188000000000" remote="126811188000000000" testing="0" />
<file name="spell_topborder.gif" local="126811188000000000" remote="126811188000000000" testing="0" />
</dwsync>