{
  "framerate":12,
"images": ["sprites.png"],
"frames": [

        
      [1132, 696, 136, 75, 0,  -0, -0, 145, 85], 
        
      [1132, 773, 136, 75, 0,  -0, -0, 145, 85], 
        
      [859, 430, 129, 56, 0,  -16, -29, 145, 85], 
        
      [2, 405, 340, 391, 0,  -0, -0, 340, 391], 
        
      [1244, 605, 56, 51, 0,  -0, -0, 56, 51], 
        
      [1132, 850, 56, 51, 0,  -0, -0, 56, 51], 
        
      [623, 2, 251, 287, 0,  -26, -8, 281, 295], 
        
      [371, 2, 250, 289, 0,  -21, -6, 281, 295], 
        
      [876, 2, 247, 291, 0,  -7, -4, 281, 295], 
        
      [1125, 2, 246, 292, 0,  -0, -3, 281, 295], 
        
      [671, 291, 186, 133, 0,  -0, -0, 186, 133], 
        
      [859, 295, 186, 133, 0,  -0, -0, 186, 133], 
        
      [671, 426, 186, 133, 0,  -0, -0, 186, 133], 
        
      [944, 696, 186, 133, 0,  -0, -0, 186, 133], 
        
      [944, 831, 186, 133, 0,  -0, -0, 186, 133], 
        
      [371, 293, 298, 199, 0,  -0, -3, 300, 205], 
        
      [344, 698, 298, 196, 0,  -0, -5, 300, 205], 
        
      [344, 494, 298, 202, 0,  -0, -3, 300, 205], 
        
      [1047, 296, 298, 198, 0,  -0, -0, 300, 205], 
        
      [644, 761, 298, 194, 0,  -0, -3, 300, 205], 
        
      [2, 798, 298, 193, 0,  -0, -5, 300, 205], 
        
      [644, 561, 298, 198, 0,  -0, -3, 300, 205], 
        
      [944, 496, 298, 198, 0,  -0, -0, 300, 205], 
        
      [371, 293, 298, 199, 0,  -0, -3, 300, 205], 
        
      [2, 2, 367, 401, 0,  -0, -0, 367, 401], 
        
      [1244, 496, 99, 107, 0,  -0, -0, 99, 107]
],
"animations": {
        "coco-eyes":{"frames":[0,0,0,0,0,0,0,0,2,2,2,0,0,0,0,0,0,0,0,0,1,1,1,1,1,1,1,0,0,0,0,0,0,0,0,0,0,0,0,0],"speed":0.4}, 
        "coco":[3], 
        "glove-x":[4], 
        "glove":[5], 
        "mouse-stand":[6],
        "mouse-wave":{"frames":[6,6,6,6,6,6,6,6,6,6,6,6,6,6,6,6,6,7,8,9,8,9,8,9,8,9,8,9,8,7],"next":"mouse-stand","speed":0.8},
        "mouse-head":[10],
        "mouse-head-good":{"frames":[11,12,12,12,12,12,12],"next":"mouse-head","speed":0.4},
        "mouse-head-bad":{"frames":[13,14,14,14,14,14,14],"next":"mouse-head","speed":0.4},
        "mouse-walk-1":[15], 
        "mouse-walk-2":[16], 
        "mouse-walk-3":[17], 
        "mouse-walk-4":[18], 
        "mouse-walk-5":[19], 
        "mouse-walk-6":[20], 
        "mouse-walk-7":[21], 
        "mouse-walk-8":[22], 
        "mouse-walk-9":[23], 
        "sign":[24], 
        "x-purple":[25]
},
"texturepacker": [
        "SmartUpdateHash: $TexturePacker:SmartUpdate:f7480d995d39f28cae10453f99b4d2a9:e000dee533e5fb278c608f5524d2d0d2:aeeb9bbe8ff332cc652cb8e53d41783e$",
        "EaselJS Extended Exporter - Trim support"
]
}