<game id="flyer" hasSponsorBar="true">
	<title><![CDATA[SUPER WHY! . GAMES . SUPERWHY FLYER | PBS KIDS]]></title>
	<swf url="../sections/games/flyer/flyer.swf" />
	
	<settings
		difficultyIsAdjustable = "false"
		helpIsActive = "false"
		hasPrintable = "true"
	/>

	
	<libraries>
		<library id="burbankbigcdttbdembedded" url="../libraries/burbankbigcdttbdembedded.swf" type="font" name="BurbankBigCdTTBdEmbedded" font="BurbankBigCdTTBdEmbeddedFont" />
		<library id="futuratdemeduembedded" url="../libraries/futuratdemeduembedded.swf" type="font" name="FuturaTDemEduEmbedded" font="FuturaTDemEduEmbeddedFont"/>
		<library id="superwhy_endscreen" url="../libraries/superwhy_endscreen.swf" />
	</libraries> 

	<assets>
		
		<letters id="letters" isGroup="true">
			<letter id="a" type="audio" url="../sections/games/flyer/audio/letters/a_pp.mp3"/>
			<letter id="b" type="audio" url="../sections/games/flyer/audio/letters/b_pp.mp3"/>
		</letters>
		
		<oops id="oops" isGroup="true">
			<oops id="keep_looking" type="audio" url="../sections/games/flyer/audio/oops/keep_looking.mp3" />
			<oops id="keep_rolling" type="audio" url="../sections/games/flyer/audio/oops/keep_rolling.mp3" />
		</oops>
		
		<kudos id="kudos" isGroup="true">
			<kudos id="wonderiffic" type="audio" url="../sections/games/flyer/audio/kudos/wonderiffic.mp3" />
			<kudos id="you_got_it.mp3" type="audio" url="../sections/games/flyer/audio/kudos/you_got_it.mp3" />
		</kudos>
		
		<soundfx id="soundfx" isGroup="true">
			<soundfx id="zap" type="audio" url="../sections/games/flyer/audio/sfx/sfx_UI_over.mp3" />
			<soundfx id="zap2" type="audio" url="../sections/games/flyer/audio/sfx/sfx_UI_press.mp3" />
		</soundfx>
		
		<prompts id="prompts" isGroup="true">
			<prompt id="find_letter" type="audio" url="../sections/games/flyer/audio/prompts/find_letter.mp3" />
			<prompt id="find_letter2" type="audio" url="../sections/games/flyer/audio/prompts/find_letter.mp3" />
		</prompts>
		

	</assets>
	

</game>
